finders/__init__.py
finders/finder.py
finders/aws/__init__.py
finders/aws/connection_manager.py
finders/aws/paginate.py
finders/aws/stacks.py
finders-0.1.3.dist-info/LICENSE
finders-0.1.3.dist-info/METADATA
finders-0.1.3.dist-info/WHEEL
finders-0.1.3.dist-info/top_level.txt
finders-0.1.3.dist-info/RECORD
