Metadata-Version: 2.1
Name: finders
Version: 0.1.3
Summary: Finders - Find resources to determine if you want to keep them
Home-page: https://github.com/acaire/finders
Author: Ash Caire
Author-email: ash.caire@gmail.com
License: MIT
Keywords: finders,keepers,resource,discovery,aws,cloudformation,stacks
Platform: UNKNOWN
Classifier: Development Status :: 3 - Alpha
Classifier: Intended Audience :: Developers
Classifier: Natural Language :: English
Classifier: License :: OSI Approved :: MIT License
Classifier: Programming Language :: Python
Classifier: Programming Language :: Python :: 3.8
Requires-Dist: boto3
